nhlscrapy/__init__.py
nhlscrapy/nhlscrapy.py
nhlscrapy/tests/__init__.py
nhlscrapy/tests/context.py
nhlscrapy/tests/test_nhlscrapy.py
nhlscrapy-0.0.1.dist-info/METADATA
nhlscrapy-0.0.1.dist-info/RECORD
nhlscrapy-0.0.1.dist-info/WHEEL
nhlscrapy-0.0.1.dist-info/top_level.txt
