Metadata-Version: 2.1
Name: nhlscrapy
Version: 0.0.1
Summary: A fast downloader of NHL data.
Home-page: https://github.com/xaaaaav/nhlscrapy
Author: Xavier Thierry
Author-email: xaverthierry0@gmail.com
License: http://www.apache.org/licenses/LICENSE-2.0
Platform: UNKNOWN
